odoo10_addon_l10n_it_vat_registries_cash_basis-10.0.1.0.1-nspkg.pth
odoo/addons/l10n_it_vat_registries_cash_basis/README.rst
odoo/addons/l10n_it_vat_registries_cash_basis/__init__.py
odoo/addons/l10n_it_vat_registries_cash_basis/__manifest__.py
odoo/addons/l10n_it_vat_registries_cash_basis/i18n/es_AR.po
odoo/addons/l10n_it_vat_registries_cash_basis/i18n/it.po
odoo/addons/l10n_it_vat_registries_cash_basis/i18n/l10n_it_vat_registries_cash_basis.pot
odoo/addons/l10n_it_vat_registries_cash_basis/i18n/sl.po
odoo/addons/l10n_it_vat_registries_cash_basis/models/__init__.py
odoo/addons/l10n_it_vat_registries_cash_basis/models/account.py
odoo/addons/l10n_it_vat_registries_cash_basis/models/vat_registry.py
odoo/addons/l10n_it_vat_registries_cash_basis/static/description/icon.png
odoo/addons/l10n_it_vat_registries_cash_basis/tests/__init__.py
odoo/addons/l10n_it_vat_registries_cash_basis/tests/test_registry.py
odoo/addons/l10n_it_vat_registries_cash_basis/wizard/__init__.py
odoo/addons/l10n_it_vat_registries_cash_basis/wizard/print_registro_iva.py
odoo10_addon_l10n_it_vat_registries_cash_basis-10.0.1.0.1.dist-info/METADATA
odoo10_addon_l10n_it_vat_registries_cash_basis-10.0.1.0.1.dist-info/WHEEL
odoo10_addon_l10n_it_vat_registries_cash_basis-10.0.1.0.1.dist-info/namespace_packages.txt
odoo10_addon_l10n_it_vat_registries_cash_basis-10.0.1.0.1.dist-info/top_level.txt
odoo10_addon_l10n_it_vat_registries_cash_basis-10.0.1.0.1.dist-info/RECORD
